mcpeepants/__init__.py
mcpeepants/async_tools.py
mcpeepants/plugin_loader.py
mcpeepants/server.py
mcpeepants/tools.py
mcpeepants/plugins/__init__.py
mcpeepants/plugins/example_plugin.py
mcpeepants-0.1.0.dist-info/licenses/LICENSE
mcpeepants-0.1.0.dist-info/METADATA
mcpeepants-0.1.0.dist-info/WHEEL
mcpeepants-0.1.0.dist-info/entry_points.txt
mcpeepants-0.1.0.dist-info/top_level.txt
mcpeepants-0.1.0.dist-info/RECORD
