Metadata-Version: 2.4
Name: mcpeepants
Version: 0.1.0
Summary: Extensible MCP server library with plugin support
Home-page: https://github.com/gizix/MCPeePants
Author: Ewvyx
Author-email: Ewvyx <nick@idabble.biz>
License: MIT
Project-URL: Homepage, https://github.com/gizix/MCPeePants
Project-URL: Bug Tracker, https://github.com/gizix/MCPeePants/issues
Project-URL: Documentation, https://github.com/gizix/MCPeePants#readme
Classifier: Development Status :: 3 - Alpha
Classifier: Intended Audience :: Developers
Classifier: Topic :: Software Development :: Libraries :: Python Modules
Classifier: License :: OSI Approved :: MIT License
Classifier: Programming Language :: Python :: 3
Classifier: Programming Language :: Python :: 3.10
Classifier: Programming Language :: Python :: 3.11
Classifier: Programming Language :: Python :: 3.12
Classifier: Operating System :: OS Independent
Requires-Python: >=3.10
License-File: LICENSE
Requires-Dist: fastmcp>=0.1.0
Requires-Dist: python-dotenv>=1.0.0
Requires-Dist: pytest>=7.0.0
Provides-Extra: dev
Requires-Dist: pytest-cov>=4.0.0; extra == "dev"
Requires-Dist: pytest-asyncio>=0.21.0; extra == "dev"
Dynamic: author
Dynamic: home-page
Dynamic: license-file
Dynamic: requires-python
